garbevents/__init__.py
garbevents/argo_events.py
garbevents/capture.py
garbevents/custom_sensors_events.py
garbevents/db.py
garbevents/events.py
garbevents/flowfilter.py
garbevents/growingio_events.py
garbevents/mock.py
garbevents/modifyrules.py
garbevents/sensors_backstage_events.py
garbevents/sensors_events.py
garbevents/settings.py
garbevents/toolbox.py
garbevents/cli/__init__.py
garbevents/cli/main.py
garbevents/mod/__init__.py
garbevents/mod/maplocals.py
garbevents/mod/mapremotes.py
garbevents/mod/mockevents.py
garbevents/mod/modifybodys.py
garbevents/mod/weaknets.py
garbevents/web/__init__.py
garbevents/web/app.py
garbevents/web/master.py
garbevents/web/static_viewer.py
garbevents/web/webaddons.py
garbevents/web/static/app.css
garbevents/web/static/app.css.map
garbevents/web/static/app.js
garbevents/web/static/app.js.map
garbevents/web/static/vendor.css
garbevents/web/static/vendor.css.map
garbevents/web/static/fonts/fontawesome-webfont.eot
garbevents/web/static/fonts/fontawesome-webfont.svg
garbevents/web/static/fonts/fontawesome-webfont.ttf
garbevents/web/static/fonts/fontawesome-webfont.woff
garbevents/web/static/fonts/fontawesome-webfont.woff2
garbevents/web/static/images/fav.ico
garbevents/web/static/images/garbevents.ico
garbevents/web/static/images/resourceExecutableIcon.png
garbevents/web/static/images/resourceFlashIcon.png
garbevents/web/static/images/resourceImageIcon.png
garbevents/web/static/images/resourceJavaIcon.png
garbevents/web/static/images/resourceNotModifiedIcon.png
garbevents/web/static/images/resourceRedirectIcon.png
garbevents/web/static/images/resourceTcpIcon.png
garbevents/web/static/images/resourceWebSocketIcon.png
garbevents/web/static/images/chrome-devtools/LICENSE
garbevents/web/static/images/chrome-devtools/resourceCSSIcon.png
garbevents/web/static/images/chrome-devtools/resourceDocumentIcon.png
garbevents/web/static/images/chrome-devtools/resourceJSIcon.png
garbevents/web/static/images/chrome-devtools/resourcePlainIcon.png
garbevents-2.1.9.dist-info/LICENSE
garbevents-2.1.9.dist-info/METADATA
garbevents-2.1.9.dist-info/WHEEL
garbevents-2.1.9.dist-info/entry_points.txt
garbevents-2.1.9.dist-info/top_level.txt
garbevents-2.1.9.dist-info/RECORD
