Metadata-Version: 2.2
Name: garbevents
Version: 2.1.9
Summary: grabbing buried points tools.
Home-page: https://github.com/Pactortester/garbevents
Author: lijiawei
Author-email: jiawei.li2@qq.com
License: MIT Licence
Keywords: pip,garbevents,zhugeio,buried points,sensors,argo,growingio
Platform: any
Classifier: License :: OSI Approved :: MIT License
Classifier: Development Status :: 5 - Production/Stable
Classifier: Environment :: Console :: Curses
Classifier: Operating System :: MacOS
Classifier: Operating System :: POSIX
Classifier: Operating System :: Microsoft :: Windows
Classifier: Programming Language :: Python :: 3 :: Only
Classifier: Programming Language :: Python :: 3.8
Classifier: Programming Language :: Python :: 3.9
Classifier: Programming Language :: Python :: 3.10
Classifier: Programming Language :: Python :: Implementation :: CPython
Classifier: Topic :: Security
Classifier: Topic :: Internet :: WWW/HTTP
Classifier: Topic :: Internet :: Proxy Servers
Classifier: Topic :: System :: Networking :: Monitoring
Classifier: Topic :: Software Development :: Testing
Classifier: Typing :: Typed
Requires-Python: >=3.8
License-File: LICENSE
Requires-Dist: mitmproxy==8.0.0
Requires-Dist: jsonpath
Requires-Dist: emoji
Requires-Dist: deepdiff
Requires-Dist: jmespath
Requires-Dist: loguru
Dynamic: author
Dynamic: author-email
Dynamic: classifier
Dynamic: description
Dynamic: description-content-type
Dynamic: home-page
Dynamic: keywords
Dynamic: license
Dynamic: platform
Dynamic: requires-dist
Dynamic: requires-python
Dynamic: summary
